<?xml version="1.0" encoding="UTF-8"?>
<faces-config>
  <managed-bean>
    <managed-bean-name>connections</managed-bean-name>
    <!--  SSO authentication Bean-->
    <managed-bean-class>com.ibm.sbt.services.endpoints.ConnectionsSSOEndpoint</managed-bean-class>
    <!--  Basic authentication Bean -->
    <!--    <managed-bean-class>com.ibm.sbt.services.endpoints.ConnectionsBasicEndpoint</managed-bean-class>-->
    <managed-bean-scope>session</managed-bean-scope>
    <managed-property>
      <property-name>url</property-name>
      <value>https://qs.renovations.com:444</value>
    </managed-property>
    <!-- Trust the connection -->
    <managed-property>
      <property-name>forceTrustSSLCertificate</property-name>
      <value>true</value>
    </managed-property>
    <!-- Basic Bean properties -->
    <!--    <managed-property>-->
    <!--      <property-name>user</property-name>-->
    <!--      <value>user</value>-->
    <!--    </managed-property>-->
    <!--    <managed-property>-->
    <!--      <property-name>password</property-name>-->
    <!--      <value>password</value>-->
    <!--    </managed-property>-->
  </managed-bean>
  <!--AUTOGEN-START-BUILDER: Automatically generated by IBM Domino Designer. Do not modify.-->
  <!--AUTOGEN-END-BUILDER: End of automatically generated section-->
</faces-config>
